setup.py
jts_erd/__init__.py
jts_erd/jts_erd.py
jts_erd.egg-info/PKG-INFO
jts_erd.egg-info/SOURCES.txt
jts_erd.egg-info/dependency_links.txt
jts_erd.egg-info/top_level.txt